celery_cloud/__init__.py
celery_cloud/debug_server.py
celery_cloud/logging.py
celery_cloud/settings.py
celery_cloud/entities/__init__.py
celery_cloud/entities/lambda_response.py
celery_cloud/entities/sqs_entities.py
celery_cloud/entities/task.py
celery_cloud/entities/task_result.py
celery_cloud/entities/task_route.py
celery_cloud/exceptions/__init__.py
celery_cloud/exceptions/runner_base_exception.py
celery_cloud/exceptions/runner_exceptions.py
celery_cloud/models/__init__.py
celery_cloud/models/task_model.py
celery_cloud/runners/__init__.py
celery_cloud/runners/aws_lambda.py
celery_cloud/runners/lambda_strategy.py
celery_cloud/runners/local_strategy.py
celery_cloud/runners/task_execution_strategy.py
celery_cloud/runners/task_executor.py
celery_cloud-0.1.29.dist-info/METADATA
celery_cloud-0.1.29.dist-info/WHEEL
celery_cloud-0.1.29.dist-info/licenses/LICENSE
celery_cloud-0.1.29.dist-info/RECORD
