Metadata-Version: 2.4
Name: celery-cloud
Version: 0.1.29
Summary: Celery workers in the cloud
Author-email: Linus <impalah@gmail.com>
License: MIT
License-File: LICENSE
Keywords: aws,celery,cloud,workers
Classifier: Development Status :: 4 - Beta
Classifier: Framework :: Celery
Classifier: Intended Audience :: Developers
Classifier: License :: OSI Approved :: MIT License
Classifier: Programming Language :: Python :: 3
Classifier: Topic :: Software Development :: Libraries :: Python Modules
Classifier: Topic :: System :: Distributed Computing
Requires-Python: >=3.12
Requires-Dist: boto3>=1.37.21
Requires-Dist: loguru>=0.7.3
Requires-Dist: pybreaker>=1.3.0
Requires-Dist: pydantic>=2.10.6
Requires-Dist: pynamodb>=6.0.2
Requires-Dist: python-dotenv>=1.0.1
Requires-Dist: svix-ksuid>=0.6.2
Requires-Dist: tenacity>=9.1.2
